pvpro/__init__.py
pvpro/classify.py
pvpro/estimate.py
pvpro/fit.py
pvpro/ivcurves.py
pvpro/main.py
pvpro/main_old_functions_can_delete.py
pvpro/plot.py
pvpro/plotting.py
pvpro/postprocess.py
pvpro/preprocess.py
pvpro/singlediode.py
pvpro/singlediode_interpolate.py
pvpro/data/NSRDB_data_compressed_123796_37.89_-122.26.npz
pvpro-0.0.4.dist-info/LICENSE
pvpro-0.0.4.dist-info/METADATA
pvpro-0.0.4.dist-info/WHEEL
pvpro-0.0.4.dist-info/top_level.txt
pvpro-0.0.4.dist-info/RECORD
