Metadata-Version: 2.1
Name: pvpro
Version: 0.0.4
Summary: Extract single diode model paramaters from PV power plant production data.
Home-page: https://github.com/DuraMAT/pvpro
Author: toddkarin
Author-email: pvtools.lbl@gmail.com
License: UNKNOWN
Platform: UNKNOWN
Classifier: Programming Language :: Python :: 3
Classifier: License :: OSI Approved :: MIT License
Classifier: Operating System :: OS Independent
Requires-Dist: numpy
Requires-Dist: pandas
Requires-Dist: scipy
